{"nodes": [{"id": "home_michel_documentos_projects_hive_mind_cerebro_cerebelo_diario_2026_06_06_3_md", "label": "06_3.md", "file_type": "document", "source_file": "cerebelo/diario/2026/06/06_3.md", "source_location": "L1", "content": "## DIRECTORY\n\n[[2026_3]]\n\n```display_folder_directory\n```\n"}, {"id": "06_06_3_directory", "label": "DIRECTORY", "file_type": "document", "source_file": "cerebelo/diario/2026/06/06_3.md", "source_location": "L1"}], "edges": [{"source": "home_michel_documentos_projects_hive_mind_cerebro_cerebelo_diario_2026_06_06_3_md", "target": "06_06_3_directory", "relation": "contains", "confidence": "EXTRACTED", "source_file": "cerebelo/diario/2026/06/06_3.md", "source_location": "L1", "weight": 1.0}, {"source": "home_michel_documentos_projects_hive_mind_cerebro_cerebelo_diario_2026_06_06_3_md", "target": "home_michel_documentos_projects_hive_mind_cerebro_cerebelo_diario_2026_06_2026_3_md", "relation": "references", "confidence": "EXTRACTED", "source_file": "cerebelo/diario/2026/06/06_3.md", "source_location": "L3", "weight": 1.0}], "input_tokens": 0, "output_tokens": 0}